{
    "fishingrod": {
        "rodType": 4,
        "enchantRod": {},
        "rodName": "Golden fishing rod",
        "cooldownTime": 30,
        "durabilityDefault": 350,
        "durability": 70,
        "moneyFix": 145,
        "rateBroken": [
            70,
            150
        ]
    },
    "inventory": [
        {
            "name": "Empty",
            "size": 0,
            "price": 0
        },
        {
            "name": "Empty",
            "size": 0,
            "price": 0
        },
        {
            "name": "Empty",
            "size": 0,
            "price": 0
        },
        {
            "name": "Empty",
            "size": 0,
            "price": 0
        },
        {
            "name": "Empty",
            "size": 0,
            "price": 0
        },
        {
            "name": "Empty",
            "size": 0,
            "price": 0
        },
        {
            "name": "Empty",
            "size": 0,
            "price": 0
        },
        {
            "name": "Empty",
            "size": 0,
            "price": 0
        },
        {
            "name": "Empty",
            "size": 0,
            "price": 0
        }
    ],
    "lastTimeFishing": 1627967982,
    "point": 536,
    "totalMoney": 0,
    "totalCatch": 13
}